psqlextra/__init__.py
psqlextra/_version.py
psqlextra/apps.py
psqlextra/compiler.py
psqlextra/expressions.py
psqlextra/lookups.py
psqlextra/query.py
psqlextra/sql.py
psqlextra/type_assertions.py
psqlextra/types.py
psqlextra/util.py
psqlextra/backend/__init__.py
psqlextra/backend/base.py
psqlextra/backend/base_impl.py
psqlextra/backend/introspection.py
psqlextra/backend/operations.py
psqlextra/backend/schema.py
psqlextra/backend/migrations/__init__.py
psqlextra/backend/migrations/patched_autodetector.py
psqlextra/backend/migrations/patched_migrations.py
psqlextra/backend/migrations/patched_project_state.py
psqlextra/backend/migrations/operations/__init__.py
psqlextra/backend/migrations/operations/add_default_partition.py
psqlextra/backend/migrations/operations/add_hash_partition.py
psqlextra/backend/migrations/operations/add_list_partition.py
psqlextra/backend/migrations/operations/add_range_partition.py
psqlextra/backend/migrations/operations/apply_state.py
psqlextra/backend/migrations/operations/create_materialized_view_model.py
psqlextra/backend/migrations/operations/create_partitioned_model.py
psqlextra/backend/migrations/operations/create_view_model.py
psqlextra/backend/migrations/operations/delete_default_partition.py
psqlextra/backend/migrations/operations/delete_hash_partition.py
psqlextra/backend/migrations/operations/delete_list_partition.py
psqlextra/backend/migrations/operations/delete_materialized_view_model.py
psqlextra/backend/migrations/operations/delete_partition.py
psqlextra/backend/migrations/operations/delete_partitioned_model.py
psqlextra/backend/migrations/operations/delete_range_partition.py
psqlextra/backend/migrations/operations/delete_view_model.py
psqlextra/backend/migrations/operations/partition.py
psqlextra/backend/migrations/state/__init__.py
psqlextra/backend/migrations/state/materialized_view.py
psqlextra/backend/migrations/state/model.py
psqlextra/backend/migrations/state/partitioning.py
psqlextra/backend/migrations/state/view.py
django_postgres_extra-2.0.8.dist-info/LICENSE
django_postgres_extra-2.0.8.dist-info/METADATA
django_postgres_extra-2.0.8.dist-info/WHEEL
django_postgres_extra-2.0.8.dist-info/top_level.txt
django_postgres_extra-2.0.8.dist-info/RECORD
