Metadata-Version: 2.1
Name: django-postgres-extra
Version: 2.0.8
Summary: Bringing all of PostgreSQL's awesomeness to Django.
Home-page: https://github.com/SectorLabs/django-postgres-extra
Author: Sector Labs
Author-email: open-source@sectorlabs.ro
License: MIT License
Keywords: django,postgres,extra,hstore,ltree
Classifier: Environment :: Web Environment
Classifier: Framework :: Django
Classifier: Intended Audience :: Developers
Classifier: License :: OSI Approved :: MIT License
Classifier: Operating System :: OS Independent
Classifier: Programming Language :: Python
Classifier: Programming Language :: Python :: 3.6
Classifier: Programming Language :: Python :: 3.7
Classifier: Programming Language :: Python :: 3.8
Classifier: Programming Language :: Python :: 3.9
Classifier: Topic :: Internet :: WWW/HTTP
Classifier: Topic :: Internet :: WWW/HTTP :: Dynamic Content
Requires-Python: >=3.6
Provides-Extra: docs
Provides-Extra: test
Provides-Extra: analysis
Provides-Extra: publish
License-File: LICENSE
